.coveragerc
.pylintrc
MANIFEST.in
README.rst
setup.cfg
setup.py
tox.ini
etc/Dockerfile
etc/docker-robottests
etc/docker_cmd
etc/sshd_config
robottests/MyCreator.py
robottests/filehelper.py
robottests/sourcedict.sh
robottests/targethosts.py
robottests/test_remotesession.robot
src/crl/__init__.py
src/crl.remotesession.egg-info/PKG-INFO
src/crl.remotesession.egg-info/SOURCES.txt
src/crl.remotesession.egg-info/dependency_links.txt
src/crl.remotesession.egg-info/entry_points.txt
src/crl.remotesession.egg-info/namespace_packages.txt
src/crl.remotesession.egg-info/requires.txt
src/crl.remotesession.egg-info/top_level.txt
src/crl/remotesession/__init__.py
src/crl/remotesession/_version.py
src/crl/remotesession/envcreatorbase.py
src/crl/remotesession/exceptions.py
src/crl/remotesession/remotesession.py
src/crl/remotesession/remotesessionbase.py
src/crl/remotesession/remotesessionexec.py
src/crl/remotesession/remotesessionfile.py
src/crl/remotesession/remotesessiontarget.py
src/crl/remotesession/robotdocsconf.py
tests/__init__.py
tests/atestexample_envcreator.py
tests/atestsessionenv.py
tests/conftest.py
tests/example_envcreator.py
tests/execsubprocess.py
tests/sessionenv.py
tests/sessionenvbase.py
tests/test_exceptions.py
tests/test_remotesessionbase.py
tests/test_remotesessionexec.py
tests/test_remotesessionfile.py
tests/test_remotesessiontarget.py
tests/utils.py