Metadata-Version: 1.1
Name: crl.remotesession
Version: 1.2.2
Summary: Remote shell command executor.
Home-page: https://github.com/nokia/crl-remotesession
Author: Petri Huovinen
Author-email: petri.huovinen@nokia.com
License: BSD-3-Clause
Keywords: robotframework
Platform: UNKNOWN
Classifier: Intended Audience :: Developers
Classifier: License :: OSI Approved :: BSD License
Classifier: Programming Language :: Python :: 2
Classifier: Programming Language :: Python :: 2.7
Classifier: Programming Language :: Python :: 3
Classifier: Programming Language :: Python :: 3.7
Classifier: Topic :: Software Development
